<?xml version="1.0" encoding="UTF-8"?>

<!-- generated on 03/30/21 23:24:10 by Eclipse SUMO sumo Version 1.8.0
<configuration xmlns:xsi="http://www.w3.org/2001/XMLSchema-instance" xsi:noNamespaceSchemaLocation="http://sumo.dlr.de/xsd/sumoConfiguration.xsd">

    <input>
        <net-file value="Roadworks\BaselinePenetration3\../RoadworksIntersection.net.xml"/>
        <route-files value="Roadworks\BaselinePenetration3\Route-Files/L4-CV-Route.rou.xml,Roadworks\BaselinePenetration3\Route-Files/L4-AV-Route.rou.xml,Roadworks\BaselinePenetration3\Route-Files/L2-CV-Route.rou.xml,Roadworks\BaselinePenetration3\Route-Files/L2-AV-Route.rou.xml,Roadworks\BaselinePenetration3\Route-Files/L0-HDV-Route.rou.xml"/>
        <additional-files value="Roadworks\BaselinePenetration3\../Additional-Files/Roadworks-Detectors.add.xml,Roadworks\BaselinePenetration3\../Additional-Files/Roadworks-Rerouters.add.xml,Roadworks\BaselinePenetration3\../Additional-Files/Roadworks-Traffic-lights.add.xml,Roadworks\BaselinePenetration3\../Additional-Files/Roadworks-Traffic-Signs.add.xml,Roadworks\BaselinePenetration3\PreparingVehicleModels/Vehicle-Models/L4-CV.add.xml,Roadworks\BaselinePenetration3\PreparingVehicleModels/Vehicle-Models/L4-CV-Left.add.xml,Roadworks\BaselinePenetration3\PreparingVehicleModels/Vehicle-Models/L4-CV-Right.add.xml,Roadworks\BaselinePenetration3\PreparingVehicleModels/Vehicle-Models/L4-AV.add.xml,Roadworks\BaselinePenetration3\PreparingVehicleModels/Vehicle-Models/L4-AV-Left.add.xml,Roadworks\BaselinePenetration3\PreparingVehicleModels/Vehicle-Models/L4-AV-Right.add.xml,Roadworks\BaselinePenetration3\PreparingVehicleModels/Vehicle-Models/L2-CV.add.xml,Roadworks\BaselinePenetration3\PreparingVehicleModels/Vehicle-Models/L2-CV-Left.add.xml,Roadworks\BaselinePenetration3\PreparingVehicleModels/Vehicle-Models/L2-CV-Right.add.xml,Roadworks\BaselinePenetration3\PreparingVehicleModels/Vehicle-Models/L2-AV.add.xml,Roadworks\BaselinePenetration3\PreparingVehicleModels/Vehicle-Models/L2-AV-Left.add.xml,Roadworks\BaselinePenetration3\PreparingVehicleModels/Vehicle-Models/L2-AV-Right.add.xml,Roadworks\BaselinePenetration3\PreparingVehicleModels/Vehicle-Models/L0-HDV.add.xml,Roadworks\BaselinePenetration3\PreparingVehicleModels/Vehicle-Models/L0-HDV-Left.add.xml,Roadworks\BaselinePenetration3\PreparingVehicleModels/Vehicle-Models/L0-HDV-Straight.add.xml"/>
    </input>

    <output>
        <tripinfo-output value="Roadworks\BaselinePenetration3\Output-Files\TripInfo.xml"/>
    </output>

    <time>
        <begin value="0"/>
        <step-length value="0.1"/>
    </time>

    <processing>
        <ignore-route-errors value="true"/>
        <waiting-time-memory value="300"/>
        <default.action-step-length value="0.1"/>
    </processing>

    <report>
        <no-warnings value="true"/>
    </report>

    <emissions>
        <device.emissions.probability value="1"/>
    </emissions>

    <traci_server>
        <remote-port value="57018"/>
    </traci_server>

    <gui_only>
        <quit-on-end value="true"/>
        <start value="true"/>
        <tracker-interval value="0.1"/>
    </gui_only>

</configuration>
-->

<SSMLog>
    <conflict begin="72.00" end="84.30" ego="L0-HDV-3" foe="L2-CV-6">
        <minTTC time="74.50" position="495.72,500.95" type="10" value="0.86"/>
        <maxDRAC time="74.50" position="495.72,500.95" type="10" value="0.16"/>
        <PET time="76.23" position="495.72,500.95" type="17" value="0.79"/>
    </conflict>
    <conflict begin="61.50" end="120.20" ego="L0-HDV-2" foe="L2-AV-3">
        <minTTC time="112.50" position="503.57,500.61" type="10" value="1.27"/>
        <maxDRAC time="112.60" position="501.61,503.18" type="11" value="2.45"/>
        <PET time="NA" position="NA" type="NA" value="NA"/>
    </conflict>
    <conflict begin="73.00" end="134.00" ego="L0-HDV-2" foe="L2-CV-9">
        <minTTC time="113.40" position="501.61,503.18" type="11" value="0.70"/>
        <maxDRAC time="NA" position="NA" type="NA" value="NA"/>
        <PET time="NA" position="NA" type="NA" value="NA"/>
    </conflict>
    <conflict begin="84.20" end="133.40" ego="L0-HDV-2" foe="L2-CV-15">
        <minTTC time="113.40" position="501.61,503.18" type="11" value="0.70"/>
        <maxDRAC time="NA" position="NA" type="NA" value="NA"/>
        <PET time="NA" position="NA" type="NA" value="NA"/>
    </conflict>
    <conflict begin="98.30" end="132.80" ego="L0-HDV-2" foe="L2-CV-18">
        <minTTC time="113.30" position="501.61,503.18" type="11" value="0.70"/>
        <maxDRAC time="112.60" position="501.61,503.18" type="11" value="0.00"/>
        <PET time="NA" position="NA" type="NA" value="NA"/>
    </conflict>
    <conflict begin="98.60" end="134.00" ego="L0-HDV-2" foe="L2-CV-16">
        <minTTC time="113.40" position="501.61,503.18" type="11" value="0.70"/>
        <maxDRAC time="NA" position="NA" type="NA" value="NA"/>
        <PET time="NA" position="NA" type="NA" value="NA"/>
    </conflict>
    <conflict begin="197.90" end="311.20" ego="L0-HDV-15" foe="L2-AV-42">
        <minTTC time="200.50" position="480.40,495.20" type="2" value="1.20"/>
        <maxDRAC time="198.80" position="480.40,495.20" type="2" value="2.93"/>
        <PET time="NA" position="NA" type="NA" value="NA"/>
    </conflict>
    <conflict begin="251.10" end="312.10" ego="L0-HDV-17" foe="L4-CV-31">
        <minTTC time="279.00" position="504.53,499.70" type="11" value="0.71"/>
        <maxDRAC time="NA" position="NA" type="NA" value="NA"/>
        <PET time="NA" position="NA" type="NA" value="NA"/>
    </conflict>
    <conflict begin="272.40" end="311.60" ego="L0-HDV-17" foe="L2-CV-67">
        <minTTC time="279.20" position="504.53,499.70" type="11" value="0.75"/>
        <maxDRAC time="278.60" position="504.53,499.70" type="11" value="0.18"/>
        <PET time="NA" position="NA" type="NA" value="NA"/>
    </conflict>
    <conflict begin="274.00" end="311.00" ego="L0-HDV-17" foe="L4-CV-34">
        <minTTC time="279.20" position="504.53,499.70" type="11" value="0.75"/>
        <maxDRAC time="278.60" position="504.53,499.70" type="11" value="0.23"/>
        <PET time="NA" position="NA" type="NA" value="NA"/>
    </conflict>
    <conflict begin="281.10" end="348.20" ego="L0-HDV-23" foe="L4-CV-31">
        <minTTC time="340.60" position="501.61,503.18" type="11" value="0.83"/>
        <maxDRAC time="340.70" position="501.61,503.18" type="11" value="2.77"/>
        <PET time="NA" position="NA" type="NA" value="NA"/>
    </conflict>
    <conflict begin="308.80" end="374.80" ego="L0-HDV-23" foe="L4-AV-39">
        <minTTC time="341.30" position="501.61,503.18" type="11" value="0.65"/>
        <maxDRAC time="NA" position="NA" type="NA" value="NA"/>
        <PET time="NA" position="NA" type="NA" value="NA"/>
    </conflict>
    <conflict begin="322.30" end="374.70" ego="L0-HDV-23" foe="L2-CV-77">
        <minTTC time="341.30" position="501.61,503.18" type="11" value="0.65"/>
        <maxDRAC time="NA" position="NA" type="NA" value="NA"/>
        <PET time="NA" position="NA" type="NA" value="NA"/>
    </conflict>
    <conflict begin="323.90" end="374.20" ego="L0-HDV-23" foe="L2-CV-78">
        <minTTC time="341.40" position="501.61,503.18" type="11" value="0.65"/>
        <maxDRAC time="340.70" position="501.61,503.18" type="11" value="0.00"/>
        <PET time="NA" position="NA" type="NA" value="NA"/>
    </conflict>
    <conflict begin="338.90" end="373.20" ego="L0-HDV-23" foe="L2-AV-82">
        <minTTC time="341.30" position="501.61,503.18" type="11" value="0.65"/>
        <maxDRAC time="340.60" position="506.37,500.57" type="10" value="0.01"/>
        <PET time="NA" position="NA" type="NA" value="NA"/>
    </conflict>
    <conflict begin="359.50" end="368.50" ego="L0-HDV-23" foe="L4-AV-46">
        <minTTC time="NA" position="NA" type="NA" value="NA"/>
        <maxDRAC time="NA" position="NA" type="NA" value="NA"/>
        <PET time="363.72" position="501.61,503.18" type="17" value="0.66"/>
    </conflict>
    <conflict begin="351.90" end="414.20" ego="L0-HDV-29" foe="L4-CV-43">
        <minTTC time="354.80" position="563.05,508.00" type="2" value="1.49"/>
        <maxDRAC time="352.00" position="565.09,508.00" type="2" value="2.62"/>
        <PET time="NA" position="NA" type="NA" value="NA"/>
    </conflict>
    <conflict begin="356.70" end="430.30" ego="L0-HDV-30" foe="L4-CV-45">
        <minTTC time="359.50" position="526.39,504.80" type="2" value="1.29"/>
        <maxDRAC time="356.70" position="527.70,504.80" type="2" value="2.83"/>
        <PET time="NA" position="NA" type="NA" value="NA"/>
    </conflict>
    <conflict begin="410.10" end="428.00" ego="L0-HDV-32" foe="L2-AV-106">
        <minTTC time="416.50" position="504.53,499.70" type="11" value="0.91"/>
        <maxDRAC time="410.10" position="500.54,494.99" type="10" value="0.35"/>
        <PET time="NA" position="NA" type="NA" value="NA"/>
    </conflict>
    <conflict begin="410.10" end="427.90" ego="L0-HDV-32" foe="L2-AV-92">
        <minTTC time="416.50" position="504.53,499.70" type="11" value="0.91"/>
        <maxDRAC time="NA" position="NA" type="NA" value="NA"/>
        <PET time="NA" position="NA" type="NA" value="NA"/>
    </conflict>
    <conflict begin="410.10" end="427.20" ego="L0-HDV-32" foe="L2-CV-103">
        <minTTC time="416.40" position="504.53,499.70" type="11" value="0.95"/>
        <maxDRAC time="416.30" position="504.53,499.70" type="11" value="0.00"/>
        <PET time="NA" position="NA" type="NA" value="NA"/>
    </conflict>
    <conflict begin="410.10" end="424.20" ego="L0-HDV-32" foe="L4-AV-23">
        <minTTC time="416.40" position="504.53,499.70" type="11" value="0.95"/>
        <maxDRAC time="416.50" position="504.53,499.70" type="11" value="0.00"/>
        <PET time="NA" position="NA" type="NA" value="NA"/>
    </conflict>
    <conflict begin="415.70" end="426.30" ego="L0-HDV-32" foe="L4-CV-54">
        <minTTC time="416.50" position="504.53,499.70" type="11" value="0.91"/>
        <maxDRAC time="415.90" position="504.00,498.49" type="10" value="0.87"/>
        <PET time="NA" position="NA" type="NA" value="NA"/>
    </conflict>
    <conflict begin="366.90" end="427.50" ego="L0-HDV-12" foe="L2-AV-95">
        <minTTC time="396.10" position="495.72,500.95" type="11" value="0.63"/>
        <maxDRAC time="NA" position="NA" type="NA" value="NA"/>
        <PET time="NA" position="NA" type="NA" value="NA"/>
    </conflict>
    <conflict begin="392.70" end="427.50" ego="L0-HDV-12" foe="L2-AV-102">
        <minTTC time="396.10" position="495.72,500.95" type="11" value="0.63"/>
        <maxDRAC time="393.20" position="499.54,506.64" type="10" value="1.91"/>
        <PET time="NA" position="NA" type="NA" value="NA"/>
    </conflict>
    <conflict begin="445.80" end="490.10" ego="L0-HDV-35" foe="L2-AV-109">
        <minTTC time="479.50" position="501.61,503.18" type="11" value="0.89"/>
        <maxDRAC time="NA" position="NA" type="NA" value="NA"/>
        <PET time="NA" position="NA" type="NA" value="NA"/>
    </conflict>
    <conflict begin="447.30" end="490.00" ego="L0-HDV-35" foe="L4-AV-59">
        <minTTC time="479.50" position="501.61,503.18" type="11" value="0.89"/>
        <maxDRAC time="447.90" position="506.37,500.57" type="10" value="2.22"/>
        <PET time="NA" position="NA" type="NA" value="NA"/>
    </conflict>
    <conflict begin="470.70" end="489.40" ego="L0-HDV-35" foe="L0-HDV-40">
        <minTTC time="479.50" position="501.61,503.18" type="11" value="0.89"/>
        <maxDRAC time="473.30" position="506.37,500.57" type="10" value="0.10"/>
        <PET time="NA" position="NA" type="NA" value="NA"/>
    </conflict>
    <conflict begin="476.50" end="488.70" ego="L0-HDV-35" foe="L2-CV-126">
        <minTTC time="479.50" position="501.61,503.18" type="11" value="0.89"/>
        <maxDRAC time="476.50" position="506.37,500.57" type="10" value="1.04"/>
        <PET time="NA" position="NA" type="NA" value="NA"/>
    </conflict>
    <conflict begin="478.50" end="487.60" ego="L0-HDV-35" foe="L4-AV-60">
        <minTTC time="479.50" position="501.61,503.18" type="11" value="0.89"/>
        <maxDRAC time="479.40" position="502.31,503.66" type="10" value="0.02"/>
        <PET time="NA" position="NA" type="NA" value="NA"/>
    </conflict>
    <conflict begin="470.70" end="536.40" ego="L0-HDV-40" foe="L4-AV-23">
        <minTTC time="519.80" position="504.53,499.70" type="11" value="0.73"/>
        <maxDRAC time="507.80" position="504.53,499.70" type="11" value="0.26"/>
        <PET time="534.02" position="501.15,495.20" type="17" value="7.58"/>
    </conflict>
    <conflict begin="483.20" end="536.30" ego="L0-HDV-40" foe="L2-CV-128">
        <minTTC time="519.80" position="504.53,499.70" type="11" value="0.73"/>
        <maxDRAC time="NA" position="NA" type="NA" value="NA"/>
        <PET time="NA" position="NA" type="NA" value="NA"/>
    </conflict>
    <conflict begin="492.00" end="536.30" ego="L0-HDV-40" foe="L2-AV-129">
        <minTTC time="519.80" position="504.53,499.70" type="11" value="0.73"/>
        <maxDRAC time="NA" position="NA" type="NA" value="NA"/>
        <PET time="NA" position="NA" type="NA" value="NA"/>
    </conflict>
    <conflict begin="517.00" end="532.50" ego="L0-HDV-40" foe="L2-AV-49">
        <minTTC time="519.80" position="504.53,499.70" type="11" value="0.73"/>
        <maxDRAC time="519.30" position="501.15,498.40" type="10" value="0.00"/>
        <PET time="NA" position="NA" type="NA" value="NA"/>
    </conflict>
    <conflict begin="329.20" end="516.70" ego="L0-HDV-26" foe="L0-HDV-27">
        <minTTC time="332.30" position="416.25,498.40" type="3" value="1.41"/>
        <maxDRAC time="329.20" position="416.25,498.40" type="3" value="2.36"/>
        <PET time="NA" position="NA" type="NA" value="NA"/>
    </conflict>
    <conflict begin="524.80" end="599.30" ego="L0-HDV-45" foe="L2-CV-128">
        <minTTC time="527.20" position="504.80,483.60" type="2" value="1.14"/>
        <maxDRAC time="524.80" position="504.80,483.60" type="2" value="3.72"/>
        <PET time="NA" position="NA" type="NA" value="NA"/>
    </conflict>
    <conflict begin="329.20" end="405.90" ego="L0-HDV-27" foe="L0-HDV-26">
        <minTTC time="332.30" position="416.25,498.40" type="2" value="1.41"/>
        <maxDRAC time="329.20" position="416.25,498.40" type="2" value="2.36"/>
        <PET time="NA" position="NA" type="NA" value="NA"/>
    </conflict>
    <conflict begin="571.30" end="654.90" ego="L0-HDV-24" foe="L2-AV-57">
        <minTTC time="574.10" position="472.90,495.20" type="2" value="1.21"/>
        <maxDRAC time="572.60" position="472.90,495.20" type="2" value="2.67"/>
        <PET time="NA" position="NA" type="NA" value="NA"/>
    </conflict>
    <conflict begin="644.80" end="691.80" ego="L0-HDV-56" foe="L0-HDV-53">
        <minTTC time="647.80" position="508.00,468.60" type="2" value="1.46"/>
        <maxDRAC time="644.80" position="508.00,468.60" type="2" value="2.47"/>
        <PET time="NA" position="NA" type="NA" value="NA"/>
    </conflict>
    <conflict begin="615.60" end="694.60" ego="L0-HDV-53" foe="L0-HDV-51">
        <minTTC time="618.30" position="508.00,476.10" type="2" value="1.28"/>
        <maxDRAC time="615.60" position="508.00,476.10" type="2" value="3.00"/>
        <PET time="NA" position="NA" type="NA" value="NA"/>
    </conflict>
    <conflict begin="644.80" end="691.80" ego="L0-HDV-53" foe="L0-HDV-56">
        <minTTC time="647.80" position="508.00,468.60" type="3" value="1.46"/>
        <maxDRAC time="644.80" position="508.00,468.60" type="3" value="2.47"/>
        <PET time="NA" position="NA" type="NA" value="NA"/>
    </conflict>
    <conflict begin="636.10" end="700.20" ego="L0-HDV-55" foe="L2-AV-159">
        <minTTC time="639.00" position="495.20,519.60" type="2" value="1.38"/>
        <maxDRAC time="636.10" position="495.20,519.60" type="2" value="2.66"/>
        <PET time="NA" position="NA" type="NA" value="NA"/>
    </conflict>
    <conflict begin="574.20" end="707.80" ego="L0-HDV-51" foe="L4-CV-80">
        <minTTC time="598.50" position="508.00,483.60" type="2" value="1.40"/>
        <maxDRAC time="598.40" position="508.00,483.60" type="2" value="1.09"/>
        <PET time="NA" position="NA" type="NA" value="NA"/>
    </conflict>
    <conflict begin="615.60" end="694.60" ego="L0-HDV-51" foe="L0-HDV-53">
        <minTTC time="618.30" position="508.00,476.10" type="3" value="1.28"/>
        <maxDRAC time="615.60" position="508.00,476.10" type="3" value="3.00"/>
        <PET time="NA" position="NA" type="NA" value="NA"/>
    </conflict>
    <conflict begin="574.50" end="709.80" ego="L0-HDV-52" foe="L2-CV-163">
        <minTTC time="614.50" position="504.80,483.60" type="2" value="1.35"/>
        <maxDRAC time="614.40" position="504.80,483.60" type="2" value="1.55"/>
        <PET time="NA" position="NA" type="NA" value="NA"/>
    </conflict>
    <conflict begin="715.00" end="826.30" ego="L0-HDV-65" foe="L4-AV-102">
        <minTTC time="753.30" position="498.40,527.96" type="3" value="0.67"/>
        <maxDRAC time="753.30" position="498.40,527.96" type="3" value="3.06"/>
        <PET time="NA" position="NA" type="NA" value="NA"/>
    </conflict>
    <conflict begin="769.20" end="822.80" ego="L0-HDV-63" foe="L0-HDV-67">
        <minTTC time="792.00" position="501.61,503.18" type="11" value="0.71"/>
        <maxDRAC time="NA" position="NA" type="NA" value="NA"/>
        <PET time="NA" position="NA" type="NA" value="NA"/>
    </conflict>
    <conflict begin="787.90" end="822.80" ego="L0-HDV-63" foe="L2-AV-215">
        <minTTC time="792.00" position="501.61,503.18" type="11" value="0.71"/>
        <maxDRAC time="789.50" position="506.37,500.57" type="10" value="1.60"/>
        <PET time="NA" position="NA" type="NA" value="NA"/>
    </conflict>
    <conflict begin="806.50" end="814.70" ego="L0-HDV-63" foe="L4-CV-111">
        <minTTC time="NA" position="NA" type="NA" value="NA"/>
        <maxDRAC time="NA" position="NA" type="NA" value="NA"/>
        <PET time="810.40" position="501.61,503.18" type="17" value="1.05"/>
    </conflict>
    <conflict begin="786.80" end="830.90" ego="L0-HDV-69" foe="L4-AV-101">
        <minTTC time="789.10" position="495.20,543.85" type="2" value="1.49"/>
        <maxDRAC time="786.80" position="495.20,545.07" type="2" value="3.16"/>
        <PET time="NA" position="NA" type="NA" value="NA"/>
    </conflict>
    <conflict begin="761.10" end="826.50" ego="L0-HDV-59" foe="L2-AV-79">
        <minTTC time="790.40" position="498.98,497.06" type="11" value="0.67"/>
        <maxDRAC time="NA" position="NA" type="NA" value="NA"/>
        <PET time="NA" position="NA" type="NA" value="NA"/>
    </conflict>
    <conflict begin="764.30" end="825.70" ego="L0-HDV-59" foe="L2-CV-91">
        <minTTC time="790.40" position="498.98,497.06" type="11" value="0.67"/>
        <maxDRAC time="NA" position="NA" type="NA" value="NA"/>
        <PET time="NA" position="NA" type="NA" value="NA"/>
    </conflict>
    <conflict begin="767.70" end="825.00" ego="L0-HDV-59" foe="L2-CV-124">
        <minTTC time="790.40" position="498.98,497.06" type="11" value="0.67"/>
        <maxDRAC time="NA" position="NA" type="NA" value="NA"/>
        <PET time="NA" position="NA" type="NA" value="NA"/>
    </conflict>
    <conflict begin="770.50" end="824.10" ego="L0-HDV-59" foe="L4-CV-67">
        <minTTC time="790.40" position="498.98,497.06" type="11" value="0.67"/>
        <maxDRAC time="NA" position="NA" type="NA" value="NA"/>
        <PET time="NA" position="NA" type="NA" value="NA"/>
    </conflict>
    <conflict begin="788.80" end="823.20" ego="L0-HDV-59" foe="L2-CV-141">
        <minTTC time="790.40" position="498.98,497.06" type="11" value="0.67"/>
        <maxDRAC time="NA" position="NA" type="NA" value="NA"/>
        <PET time="NA" position="NA" type="NA" value="NA"/>
    </conflict>
    <conflict begin="789.80" end="807.80" ego="L0-HDV-59" foe="L0-HDV-69">
        <minTTC time="790.40" position="498.98,497.06" type="11" value="0.67"/>
        <maxDRAC time="NA" position="NA" type="NA" value="NA"/>
        <PET time="NA" position="NA" type="NA" value="NA"/>
    </conflict>
    <conflict begin="809.40" end="818.00" ego="L0-HDV-59" foe="L2-CV-222">
        <minTTC time="NA" position="NA" type="NA" value="NA"/>
        <maxDRAC time="NA" position="NA" type="NA" value="NA"/>
        <PET time="814.57" position="498.98,497.06" type="17" value="1.83"/>
    </conflict>
    <conflict begin="809.90" end="904.00" ego="L0-HDV-71" foe="L2-AV-215">
        <minTTC time="812.60" position="519.60,501.60" type="2" value="1.19"/>
        <maxDRAC time="809.90" position="519.60,501.60" type="2" value="3.24"/>
        <PET time="NA" position="NA" type="NA" value="NA"/>
    </conflict>
    <conflict begin="832.40" end="846.90" ego="L0-HDV-71" foe="L4-AV-106">
        <minTTC time="842.90" position="469.04,501.60" type="10" value="0.06"/>
        <maxDRAC time="NA" position="NA" type="NA" value="NA"/>
        <PET time="NA" position="NA" type="NA" value="NA"/>
    </conflict>
    <conflict begin="826.30" end="926.70" ego="L0-HDV-72" foe="L2-AV-219">
        <minTTC time="828.90" position="492.00,537.39" type="2" value="1.48"/>
        <maxDRAC time="826.80" position="492.00,538.69" type="2" value="2.55"/>
        <PET time="NA" position="NA" type="NA" value="NA"/>
    </conflict>
    <conflict begin="844.70" end="937.70" ego="L0-HDV-74" foe="L2-CV-227">
        <minTTC time="847.30" position="508.00,483.60" type="2" value="1.15"/>
        <maxDRAC time="844.70" position="508.00,483.60" type="2" value="3.50"/>
        <PET time="NA" position="NA" type="NA" value="NA"/>
    </conflict>
    <conflict begin="888.40" end="984.60" ego="L0-HDV-78" foe="L2-CV-244">
        <minTTC time="891.30" position="519.60,508.00" type="2" value="1.13"/>
        <maxDRAC time="890.30" position="519.60,508.00" type="2" value="3.10"/>
        <PET time="NA" position="NA" type="NA" value="NA"/>
    </conflict>
    <conflict begin="971.60" end="1081.10" ego="L0-HDV-83" foe="L4-CV-86">
        <minTTC time="1070.80" position="495.72,500.95" type="10" value="1.00"/>
        <maxDRAC time="1070.80" position="495.72,500.95" type="10" value="2.25"/>
        <PET time="1072.92" position="495.72,500.95" type="17" value="0.80"/>
    </conflict>
    <conflict begin="1061.00" end="1142.30" ego="L0-HDV-92" foe="L2-CV-292">
        <minTTC time="1130.40" position="503.57,500.61" type="11" value="1.22"/>
        <maxDRAC time="1130.50" position="501.61,503.18" type="10" value="2.15"/>
        <PET time="NA" position="NA" type="NA" value="NA"/>
    </conflict>
    <conflict begin="1057.80" end="1161.40" ego="L0-HDV-93" foe="L2-CV-292">
        <minTTC time="1065.10" position="498.40,519.60" type="2" value="1.24"/>
        <maxDRAC time="1065.10" position="498.40,519.60" type="2" value="1.49"/>
        <PET time="NA" position="NA" type="NA" value="NA"/>
    </conflict>
    <conflict begin="1081.60" end="1165.30" ego="L0-HDV-93" foe="L2-AV-281">
        <minTTC time="1151.90" position="501.61,503.18" type="11" value="0.66"/>
        <maxDRAC time="NA" position="NA" type="NA" value="NA"/>
        <PET time="NA" position="NA" type="NA" value="NA"/>
    </conflict>
    <conflict begin="1084.90" end="1164.50" ego="L0-HDV-93" foe="L0-HDV-90">
        <minTTC time="1151.90" position="501.61,503.18" type="11" value="0.66"/>
        <maxDRAC time="NA" position="NA" type="NA" value="NA"/>
        <PET time="NA" position="NA" type="NA" value="NA"/>
    </conflict>
    <conflict begin="1088.60" end="1163.60" ego="L0-HDV-93" foe="L4-CV-143">
        <minTTC time="1151.90" position="501.61,503.18" type="11" value="0.66"/>
        <maxDRAC time="NA" position="NA" type="NA" value="NA"/>
        <PET time="NA" position="NA" type="NA" value="NA"/>
    </conflict>
    <conflict begin="1092.50" end="1162.60" ego="L0-HDV-93" foe="L2-CV-291">
        <minTTC time="1151.90" position="501.61,503.18" type="11" value="0.66"/>
        <maxDRAC time="NA" position="NA" type="NA" value="NA"/>
        <PET time="NA" position="NA" type="NA" value="NA"/>
    </conflict>
    <conflict begin="1131.70" end="1161.50" ego="L0-HDV-93" foe="L2-AV-293">
        <minTTC time="1151.90" position="501.61,503.18" type="11" value="0.66"/>
        <maxDRAC time="1147.70" position="502.31,503.66" type="10" value="0.00"/>
        <PET time="NA" position="NA" type="NA" value="NA"/>
    </conflict>
    <conflict begin="1192.00" end="1207.00" ego="L0-HDV-49" foe="L2-AV-319">
        <minTTC time="NA" position="NA" type="NA" value="NA"/>
        <maxDRAC time="NA" position="NA" type="NA" value="NA"/>
        <PET time="1200.29" position="504.53,499.70" type="17" value="1.78"/>
    </conflict>
    <conflict begin="1256.40" end="1268.50" ego="L0-HDV-110" foe="L2-CV-328">
        <minTTC time="NA" position="NA" type="NA" value="NA"/>
        <maxDRAC time="NA" position="NA" type="NA" value="NA"/>
        <PET time="1261.82" position="501.61,503.18" type="17" value="1.38"/>
    </conflict>
    <conflict begin="1159.10" end="1270.60" ego="L0-HDV-102" foe="L2-CV-320">
        <minTTC time="1162.40" position="508.00,483.60" type="2" value="1.43"/>
        <maxDRAC time="1161.10" position="508.00,483.60" type="2" value="2.29"/>
        <PET time="NA" position="NA" type="NA" value="NA"/>
    </conflict>
    <conflict begin="1106.40" end="1280.50" ego="L0-HDV-98" foe="L2-CV-297">
        <minTTC time="1109.70" position="492.00,583.14" type="2" value="1.49"/>
        <maxDRAC time="1106.90" position="492.00,583.87" type="2" value="2.26"/>
        <PET time="NA" position="NA" type="NA" value="NA"/>
    </conflict>
    <conflict begin="1209.20" end="1286.90" ego="L0-HDV-107" foe="L4-CV-167">
        <minTTC time="1211.90" position="508.00,455.04" type="2" value="1.36"/>
        <maxDRAC time="1209.20" position="508.00,453.91" type="2" value="2.92"/>
        <PET time="NA" position="NA" type="NA" value="NA"/>
    </conflict>
    <conflict begin="1187.40" end="1306.00" ego="L0-HDV-105" foe="L4-AV-163">
        <minTTC time="1189.90" position="501.60,484.47" type="2" value="1.16"/>
        <maxDRAC time="1187.40" position="501.60,484.47" type="2" value="3.44"/>
        <PET time="NA" position="NA" type="NA" value="NA"/>
    </conflict>
    <conflict begin="1156.20" end="1175.00" ego="L0-HDV-100" foe="L2-CV-322">
        <minTTC time="1158.40" position="614.60,504.80" type="3" value="1.43"/>
        <maxDRAC time="1156.20" position="616.20,504.80" type="3" value="3.05"/>
        <PET time="NA" position="NA" type="NA" value="NA"/>
    </conflict>
    <conflict begin="1298.60" end="1384.50" ego="L0-HDV-115" foe="L2-AV-357">
        <minTTC time="1301.10" position="504.80,458.50" type="2" value="1.48"/>
        <maxDRAC time="1298.70" position="504.80,456.17" type="2" value="2.88"/>
        <PET time="NA" position="NA" type="NA" value="NA"/>
    </conflict>
    <conflict begin="1280.70" end="1388.40" ego="L0-HDV-113" foe="L2-CV-354">
        <minTTC time="1283.50" position="492.00,578.61" type="2" value="1.48"/>
        <maxDRAC time="1281.60" position="492.00,579.64" type="2" value="2.41"/>
        <PET time="NA" position="NA" type="NA" value="NA"/>
    </conflict>
    <conflict begin="1423.70" end="1443.00" ego="L0-HDV-122" foe="L2-AV-223">
        <minTTC time="1427.00" position="499.06,503.01" type="11" value="6.98"/>
        <maxDRAC time="NA" position="NA" type="NA" value="NA"/>
        <PET time="1435.32" position="495.72,500.95" type="17" value="1.14"/>
    </conflict>
    <conflict begin="1317.90" end="1433.30" ego="L0-HDV-117" foe="L2-AV-361">
        <minTTC time="1343.20" position="519.60,501.60" type="2" value="1.35"/>
        <maxDRAC time="1317.90" position="623.78,501.60" type="2" value="2.19"/>
        <PET time="NA" position="NA" type="NA" value="NA"/>
    </conflict>
    <conflict begin="1340.70" end="1443.10" ego="L0-HDV-117" foe="L2-CV-140">
        <minTTC time="1423.60" position="504.53,499.70" type="11" value="0.63"/>
        <maxDRAC time="1411.80" position="504.53,499.70" type="11" value="0.27"/>
        <PET time="NA" position="NA" type="NA" value="NA"/>
    </conflict>
    <conflict begin="1374.70" end="1443.00" ego="L0-HDV-117" foe="L4-AV-191">
        <minTTC time="1423.60" position="504.53,499.70" type="11" value="0.63"/>
        <maxDRAC time="NA" position="NA" type="NA" value="NA"/>
        <PET time="NA" position="NA" type="NA" value="NA"/>
    </conflict>
    <conflict begin="1392.50" end="1443.00" ego="L0-HDV-117" foe="L2-CV-378">
        <minTTC time="1423.60" position="504.53,499.70" type="11" value="0.63"/>
        <maxDRAC time="NA" position="NA" type="NA" value="NA"/>
        <PET time="NA" position="NA" type="NA" value="NA"/>
    </conflict>
    <conflict begin="1396.80" end="1442.10" ego="L0-HDV-117" foe="L4-AV-189">
        <minTTC time="1423.60" position="504.53,499.70" type="11" value="0.63"/>
        <maxDRAC time="1411.70" position="504.53,499.70" type="11" value="0.10"/>
        <PET time="NA" position="NA" type="NA" value="NA"/>
    </conflict>
    <conflict begin="1401.20" end="1442.10" ego="L0-HDV-117" foe="L2-CV-391">
        <minTTC time="1423.50" position="504.53,499.70" type="11" value="0.64"/>
        <maxDRAC time="1407.90" position="504.53,499.70" type="11" value="0.00"/>
        <PET time="NA" position="NA" type="NA" value="NA"/>
    </conflict>
    <conflict begin="1401.50" end="1441.10" ego="L0-HDV-117" foe="L2-AV-380">
        <minTTC time="1423.60" position="504.53,499.70" type="11" value="0.63"/>
        <maxDRAC time="1412.00" position="504.53,499.70" type="11" value="0.05"/>
        <PET time="NA" position="NA" type="NA" value="NA"/>
    </conflict>
    <conflict begin="1406.90" end="1440.00" ego="L0-HDV-117" foe="L4-CV-195">
        <minTTC time="1423.60" position="504.53,499.70" type="11" value="0.63"/>
        <maxDRAC time="1411.80" position="504.53,499.70" type="11" value="0.04"/>
        <PET time="NA" position="NA" type="NA" value="NA"/>
    </conflict>
    <conflict begin="1412.50" end="1440.70" ego="L0-HDV-117" foe="L4-CV-81">
        <minTTC time="1423.60" position="504.53,499.70" type="11" value="0.63"/>
        <maxDRAC time="1412.50" position="504.53,499.70" type="11" value="0.05"/>
        <PET time="NA" position="NA" type="NA" value="NA"/>
    </conflict>
    <conflict begin="1415.40" end="1438.70" ego="L0-HDV-117" foe="L2-CV-394">
        <minTTC time="1423.60" position="504.53,499.70" type="11" value="0.63"/>
        <maxDRAC time="1423.50" position="504.53,499.70" type="11" value="0.02"/>
        <PET time="NA" position="NA" type="NA" value="NA"/>
    </conflict>
    <conflict begin="1308.80" end="1495.80" ego="L0-HDV-113" foe="L2-CV-367">
        <minTTC time="1311.80" position="492.00,581.10" type="3" value="1.22"/>
        <maxDRAC time="1308.80" position="492.00,581.36" type="3" value="6.48"/>
        <PET time="NA" position="NA" type="NA" value="NA"/>
    </conflict>
    <conflict begin="1444.00" end="1528.30" ego="L0-HDV-128" foe="L2-CV-399">
        <minTTC time="1446.90" position="498.40,527.10" type="2" value="1.38"/>
        <maxDRAC time="1444.00" position="498.40,527.11" type="2" value="2.61"/>
        <PET time="NA" position="NA" type="NA" value="NA"/>
    </conflict>
    <conflict begin="1507.60" end="1590.00" ego="L0-HDV-131" foe="L2-AV-418">
        <minTTC time="1583.50" position="498.98,497.06" type="11" value="0.69"/>
        <maxDRAC time="1583.50" position="498.98,497.06" type="11" value="2.41"/>
        <PET time="NA" position="NA" type="NA" value="NA"/>
    </conflict>
    <conflict begin="1569.60" end="1616.40" ego="L0-HDV-140" foe="L0-HDV-138">
        <minTTC time="1572.00" position="508.00,462.63" type="2" value="1.26"/>
        <maxDRAC time="1569.60" position="508.00,461.84" type="2" value="3.43"/>
        <PET time="NA" position="NA" type="NA" value="NA"/>
    </conflict>
    <conflict begin="1569.60" end="1616.40" ego="L0-HDV-138" foe="L0-HDV-140">
        <minTTC time="1572.00" position="508.00,462.63" type="3" value="1.26"/>
        <maxDRAC time="1569.60" position="508.00,461.84" type="3" value="3.43"/>
        <PET time="NA" position="NA" type="NA" value="NA"/>
    </conflict>
    <conflict begin="1539.30" end="1612.30" ego="L0-HDV-131" foe="L2-AV-179">
        <minTTC time="1583.80" position="498.98,497.06" type="11" value="0.65"/>
        <maxDRAC time="NA" position="NA" type="NA" value="NA"/>
        <PET time="NA" position="NA" type="NA" value="NA"/>
    </conflict>
    <conflict begin="1543.70" end="1611.50" ego="L0-HDV-131" foe="L2-CV-286">
        <minTTC time="1583.80" position="498.98,497.06" type="11" value="0.65"/>
        <maxDRAC time="NA" position="NA" type="NA" value="NA"/>
        <PET time="NA" position="NA" type="NA" value="NA"/>
    </conflict>
    <conflict begin="1547.70" end="1610.60" ego="L0-HDV-131" foe="L2-AV-192">
        <minTTC time="1583.80" position="498.98,497.06" type="11" value="0.65"/>
        <maxDRAC time="NA" position="NA" type="NA" value="NA"/>
        <PET time="NA" position="NA" type="NA" value="NA"/>
    </conflict>
    <conflict begin="1555.00" end="1609.50" ego="L0-HDV-131" foe="L4-CV-152">
        <minTTC time="1583.80" position="498.98,497.06" type="11" value="0.65"/>
        <maxDRAC time="NA" position="NA" type="NA" value="NA"/>
        <PET time="NA" position="NA" type="NA" value="NA"/>
    </conflict>
    <conflict begin="1581.20" end="1608.40" ego="L0-HDV-131" foe="L4-CV-157">
        <minTTC time="1583.80" position="498.98,497.06" type="11" value="0.65"/>
        <maxDRAC time="NA" position="NA" type="NA" value="NA"/>
        <PET time="NA" position="NA" type="NA" value="NA"/>
    </conflict>
    <conflict begin="1593.00" end="1602.50" ego="L0-HDV-131" foe="L2-AV-443">
        <minTTC time="NA" position="NA" type="NA" value="NA"/>
        <maxDRAC time="NA" position="NA" type="NA" value="NA"/>
        <PET time="1598.27" position="498.98,497.06" type="17" value="1.06"/>
    </conflict>
    <conflict begin="1646.20" end="1667.50" ego="L0-HDV-141" foe="L2-CV-286">
        <minTTC time="1646.80" position="499.06,503.01" type="11" value="8.76"/>
        <maxDRAC time="NA" position="NA" type="NA" value="NA"/>
        <PET time="1659.82" position="495.72,500.95" type="17" value="1.23"/>
    </conflict>
    <conflict begin="1657.40" end="1671.10" ego="L0-HDV-145" foe="L2-AV-192">
        <minTTC time="1664.50" position="499.31,494.65" type="111" value="0.00"/>
        <maxDRAC time="1663.70" position="498.72,495.20" type="12" value="12.30"/>
        <PET time="1663.67" position="498.43,489.74" type="111" value="0.00"/>
    </conflict>
    <conflict begin="1681.00" end="1757.50" ego="L0-HDV-150" foe="L2-CV-464">
        <minTTC time="1683.40" position="519.60,508.00" type="2" value="1.25"/>
        <maxDRAC time="1681.00" position="519.60,508.00" type="2" value="3.29"/>
        <PET time="NA" position="NA" type="NA" value="NA"/>
    </conflict>
    <conflict begin="1670.10" end="1828.10" ego="L0-HDV-142" foe="L2-CV-470">
        <minTTC time="1670.70" position="492.00,595.20" type="3" value="1.46"/>
        <maxDRAC time="1670.10" position="492.00,595.22" type="3" value="5.97"/>
        <PET time="NA" position="NA" type="NA" value="NA"/>
    </conflict>
    <conflict begin="1813.10" end="1825.20" ego="L0-HDV-161" foe="L2-AV-492">
        <minTTC time="NA" position="NA" type="NA" value="NA"/>
        <maxDRAC time="NA" position="NA" type="NA" value="NA"/>
        <PET time="1818.46" position="501.61,503.18" type="17" value="1.24"/>
    </conflict>
    <conflict begin="1696.60" end="1852.40" ego="L0-HDV-152" foe="L2-CV-470">
        <minTTC time="1699.40" position="492.00,602.14" type="2" value="1.28"/>
        <maxDRAC time="1696.60" position="492.00,602.19" type="2" value="2.96"/>
        <PET time="NA" position="NA" type="NA" value="NA"/>
    </conflict>
    <conflict begin="1727.00" end="1854.80" ego="L0-HDV-157" foe="L2-AV-492">
        <minTTC time="1760.90" position="498.40,519.60" type="2" value="1.27"/>
        <maxDRAC time="1760.90" position="498.40,519.60" type="2" value="1.56"/>
        <PET time="NA" position="NA" type="NA" value="NA"/>
    </conflict>
    <conflict begin="1774.70" end="1855.10" ego="L0-HDV-158" foe="L4-AV-247">
        <minTTC time="1777.60" position="501.60,468.99" type="2" value="1.29"/>
        <maxDRAC time="1774.70" position="501.60,468.99" type="2" value="2.81"/>
        <PET time="NA" position="NA" type="NA" value="NA"/>
    </conflict>
    <conflict begin="1806.80" end="1926.30" ego="L0-HDV-164" foe="L2-CV-515">
        <minTTC time="1843.90" position="504.80,483.59" type="3" value="0.65"/>
        <maxDRAC time="1843.90" position="504.80,483.59" type="3" value="3.68"/>
        <PET time="NA" position="NA" type="NA" value="NA"/>
    </conflict>
    <conflict begin="1853.90" end="1926.30" ego="L0-HDV-164" foe="L2-CV-520">
        <minTTC time="1916.70" position="501.61,503.18" type="10" value="1.00"/>
        <maxDRAC time="1916.60" position="501.61,503.18" type="10" value="2.18"/>
        <PET time="NA" position="NA" type="NA" value="NA"/>
    </conflict>
    <conflict begin="1884.90" end="1936.90" ego="L0-HDV-168" foe="L4-CV-263">
        <minTTC time="1887.80" position="508.00,468.54" type="2" value="1.26"/>
        <maxDRAC time="1885.40" position="508.00,468.34" type="2" value="2.71"/>
        <PET time="NA" position="NA" type="NA" value="NA"/>
    </conflict>
    <conflict begin="1867.90" end="1961.00" ego="L0-HDV-167" foe="L2-CV-522">
        <minTTC time="1870.40" position="504.80,453.52" type="2" value="1.35"/>
        <maxDRAC time="1868.10" position="504.80,452.16" type="2" value="2.81"/>
        <PET time="NA" position="NA" type="NA" value="NA"/>
    </conflict>
    <conflict begin="1992.80" end="2044.50" ego="L0-HDV-178" foe="L2-CV-555">
        <minTTC time="1995.30" position="504.80,476.10" type="2" value="1.23"/>
        <maxDRAC time="1992.90" position="504.80,476.10" type="2" value="3.36"/>
        <PET time="NA" position="NA" type="NA" value="NA"/>
    </conflict>
    <conflict begin="2010.00" end="2048.60" ego="L0-HDV-179" foe="L2-CV-558">
        <minTTC time="2012.90" position="508.00,461.10" type="2" value="1.32"/>
        <maxDRAC time="2010.80" position="508.00,461.10" type="2" value="2.60"/>
        <PET time="NA" position="NA" type="NA" value="NA"/>
    </conflict>
    <conflict begin="2041.60" end="2098.80" ego="L0-HDV-183" foe="L2-AV-563">
        <minTTC time="2044.00" position="501.60,466.58" type="2" value="1.42"/>
        <maxDRAC time="2041.80" position="501.60,466.23" type="2" value="2.90"/>
        <PET time="NA" position="NA" type="NA" value="NA"/>
    </conflict>
    <conflict begin="2140.00" end="2180.60" ego="L0-HDV-192" foe="L0-HDV-186">
        <minTTC time="2142.40" position="492.00,550.35" type="2" value="1.36"/>
        <maxDRAC time="2140.10" position="492.00,550.63" type="2" value="3.19"/>
        <PET time="NA" position="NA" type="NA" value="NA"/>
    </conflict>
    <conflict begin="2140.00" end="2180.60" ego="L0-HDV-186" foe="L0-HDV-192">
        <minTTC time="2142.40" position="492.00,550.35" type="3" value="1.36"/>
        <maxDRAC time="2140.10" position="492.00,550.63" type="3" value="3.19"/>
        <PET time="NA" position="NA" type="NA" value="NA"/>
    </conflict>
    <conflict begin="2131.10" end="2203.20" ego="L0-HDV-193" foe="L4-CV-304">
        <minTTC time="2167.30" position="534.61,508.00" type="3" value="1.50"/>
        <maxDRAC time="2167.30" position="534.61,508.00" type="3" value="0.99"/>
        <PET time="NA" position="NA" type="NA" value="NA"/>
    </conflict>
    <conflict begin="2144.50" end="2203.90" ego="L0-HDV-156" foe="L2-AV-602">
        <minTTC time="2194.80" position="504.53,499.70" type="10" value="0.85"/>
        <maxDRAC time="2194.70" position="504.53,499.70" type="10" value="1.72"/>
        <PET time="NA" position="NA" type="NA" value="NA"/>
    </conflict>
    <conflict begin="2162.50" end="2218.30" ego="L0-HDV-193" foe="L2-CV-604">
        <minTTC time="2165.70" position="527.12,508.00" type="2" value="1.45"/>
        <maxDRAC time="2162.50" position="527.27,508.00" type="2" value="2.18"/>
        <PET time="NA" position="NA" type="NA" value="NA"/>
    </conflict>
    <conflict begin="2184.70" end="2267.50" ego="L0-HDV-195" foe="L2-CV-614">
        <minTTC time="2256.90" position="497.04,499.75" type="11" value="1.39"/>
        <maxDRAC time="2257.00" position="498.98,497.06" type="10" value="1.89"/>
        <PET time="NA" position="NA" type="NA" value="NA"/>
    </conflict>
    <conflict begin="2250.80" end="2293.20" ego="L0-HDV-202" foe="L2-CV-630">
        <minTTC time="2253.70" position="504.80,468.60" type="2" value="1.30"/>
        <maxDRAC time="2250.80" position="504.80,468.59" type="2" value="2.71"/>
        <PET time="NA" position="NA" type="NA" value="NA"/>
    </conflict>
    <conflict begin="2208.90" end="2298.10" ego="L0-HDV-198" foe="L2-AV-614">
        <minTTC time="2211.50" position="498.40,525.41" type="2" value="1.33"/>
        <maxDRAC time="2209.00" position="498.40,525.41" type="2" value="2.92"/>
        <PET time="NA" position="NA" type="NA" value="NA"/>
    </conflict>
    <conflict begin="2218.90" end="2323.50" ego="L0-HDV-130" foe="L2-CV-605">
        <minTTC time="2312.90" position="495.72,500.95" type="11" value="0.67"/>
        <maxDRAC time="2310.30" position="499.06,503.01" type="10" value="0.60"/>
        <PET time="NA" position="NA" type="NA" value="NA"/>
    </conflict>
    <conflict begin="2222.20" end="2330.00" ego="L0-HDV-130" foe="L2-AV-606">
        <minTTC time="2312.90" position="495.72,500.95" type="11" value="0.67"/>
        <maxDRAC time="2310.90" position="495.72,500.95" type="11" value="0.61"/>
        <PET time="NA" position="NA" type="NA" value="NA"/>
    </conflict>
    <conflict begin="2292.50" end="2339.40" ego="L0-HDV-130" foe="L4-AV-323">
        <minTTC time="2312.90" position="495.72,500.95" type="11" value="0.67"/>
        <maxDRAC time="NA" position="NA" type="NA" value="NA"/>
        <PET time="NA" position="NA" type="NA" value="NA"/>
    </conflict>
    <conflict begin="2307.60" end="2331.40" ego="L0-HDV-130" foe="L0-HDV-194">
        <minTTC time="2312.90" position="495.72,500.95" type="11" value="0.67"/>
        <maxDRAC time="2310.90" position="495.72,500.95" type="11" value="0.47"/>
        <PET time="2329.00" position="495.72,500.95" type="17" value="3.31"/>
    </conflict>
    <conflict begin="2311.20" end="2338.90" ego="L0-HDV-130" foe="L2-CV-648">
        <minTTC time="2312.90" position="495.72,500.95" type="11" value="0.67"/>
        <maxDRAC time="2311.30" position="496.47,502.39" type="10" value="1.70"/>
        <PET time="NA" position="NA" type="NA" value="NA"/>
    </conflict>
    <conflict begin="2311.60" end="2333.80" ego="L0-HDV-130" foe="L0-HDV-196">
        <minTTC time="2313.00" position="495.72,500.95" type="11" value="0.68"/>
        <maxDRAC time="2312.10" position="495.72,500.95" type="11" value="0.45"/>
        <PET time="2329.00" position="495.72,500.95" type="17" value="0.84"/>
    </conflict>
    <conflict begin="2313.50" end="2336.70" ego="L0-HDV-196" foe="L0-HDV-130">
        <minTTC time="2317.90" position="499.06,503.01" type="11" value="14.29"/>
        <maxDRAC time="2313.50" position="495.72,500.95" type="10" value="0.01"/>
        <PET time="2329.00" position="495.72,500.95" type="17" value="0.84"/>
    </conflict>
    <conflict begin="2469.30" end="2545.00" ego="L0-HDV-84" foe="L4-CV-348">
        <minTTC time="2534.60" position="504.53,499.70" type="10" value="0.87"/>
        <maxDRAC time="2534.60" position="504.53,499.70" type="10" value="2.13"/>
        <PET time="2542.34" position="504.53,499.70" type="17" value="6.09"/>
    </conflict>
    <conflict begin="2587.40" end="2654.00" ego="L0-HDV-232" foe="L2-AV-516">
        <minTTC time="2589.40" position="504.53,499.70" type="11" value="2.99"/>
        <maxDRAC time="2644.70" position="504.53,499.70" type="11" value="1.14"/>
        <PET time="2649.30" position="504.53,499.70" type="17" value="1.11"/>
    </conflict>
    <conflict begin="2636.20" end="2661.10" ego="L0-HDV-232" foe="L2-AV-743">
        <minTTC time="2645.60" position="504.53,499.70" type="11" value="0.83"/>
        <maxDRAC time="NA" position="NA" type="NA" value="NA"/>
        <PET time="NA" position="NA" type="NA" value="NA"/>
    </conflict>
    <conflict begin="2641.60" end="2660.40" ego="L0-HDV-232" foe="L2-CV-746">
        <minTTC time="2645.60" position="504.53,499.70" type="11" value="0.83"/>
        <maxDRAC time="2642.50" position="504.00,498.49" type="10" value="0.60"/>
        <PET time="NA" position="NA" type="NA" value="NA"/>
    </conflict>
    <conflict begin="2867.80" end="2885.40" ego="L0-HDV-94" foe="L2-CV-799">
        <minTTC time="2876.00" position="504.53,499.70" type="10" value="0.80"/>
        <maxDRAC time="2876.00" position="504.53,499.70" type="10" value="0.23"/>
        <PET time="2877.78" position="504.53,499.70" type="17" value="0.90"/>
    </conflict>
    <conflict begin="2786.00" end="2895.80" ego="L0-HDV-253" foe="L2-CV-796">
        <minTTC time="2825.20" position="542.10,508.00" type="3" value="0.90"/>
        <maxDRAC time="2824.60" position="542.10,508.00" type="3" value="2.31"/>
        <PET time="NA" position="NA" type="NA" value="NA"/>
    </conflict>
    <conflict begin="2820.50" end="2885.20" ego="L0-HDV-253" foe="L2-CV-790">
        <minTTC time="2823.30" position="534.60,508.00" type="2" value="1.22"/>
        <maxDRAC time="2821.40" position="534.60,508.00" type="2" value="2.78"/>
        <PET time="NA" position="NA" type="NA" value="NA"/>
    </conflict>
    <conflict begin="2884.50" end="2899.90" ego="L0-HDV-248" foe="L2-CV-504">
        <minTTC time="NA" position="NA" type="NA" value="NA"/>
        <maxDRAC time="NA" position="NA" type="NA" value="NA"/>
        <PET time="2892.19" position="495.72,500.95" type="17" value="0.19"/>
    </conflict>
    <conflict begin="2819.00" end="2913.50" ego="L0-HDV-256" foe="L2-CV-805">
        <minTTC time="2853.40" position="527.10,501.60" type="3" value="1.48"/>
        <maxDRAC time="2853.20" position="527.10,501.60" type="3" value="0.93"/>
        <PET time="NA" position="NA" type="NA" value="NA"/>
    </conflict>
    <conflict begin="2904.80" end="2961.10" ego="L0-HDV-260" foe="L2-AV-526">
        <minTTC time="2925.80" position="498.98,497.06" type="11" value="0.75"/>
        <maxDRAC time="NA" position="NA" type="NA" value="NA"/>
        <PET time="NA" position="NA" type="NA" value="NA"/>
    </conflict>
    <conflict begin="2907.20" end="2960.30" ego="L0-HDV-260" foe="L0-HDV-173">
        <minTTC time="2925.80" position="498.98,497.06" type="11" value="0.75"/>
        <maxDRAC time="NA" position="NA" type="NA" value="NA"/>
        <PET time="NA" position="NA" type="NA" value="NA"/>
    </conflict>
    <conflict begin="2911.00" end="2959.50" ego="L0-HDV-260" foe="L4-CV-148">
        <minTTC time="2925.70" position="498.98,497.06" type="11" value="0.76"/>
        <maxDRAC time="2925.00" position="498.98,497.06" type="11" value="0.00"/>
        <PET time="NA" position="NA" type="NA" value="NA"/>
    </conflict>
    <conflict begin="2914.50" end="2958.60" ego="L0-HDV-260" foe="L2-CV-296">
        <minTTC time="2925.70" position="498.98,497.06" type="11" value="0.76"/>
        <maxDRAC time="2925.00" position="498.98,497.06" type="11" value="0.02"/>
        <PET time="NA" position="NA" type="NA" value="NA"/>
    </conflict>
    <conflict begin="2916.20" end="2966.60" ego="L0-HDV-260" foe="L0-HDV-262">
        <minTTC time="2918.90" position="501.60,483.60" type="3" value="1.37"/>
        <maxDRAC time="2916.40" position="501.60,483.60" type="3" value="2.77"/>
        <PET time="NA" position="NA" type="NA" value="NA"/>
    </conflict>
    <conflict begin="2923.90" end="2957.60" ego="L0-HDV-260" foe="L4-CV-155">
        <minTTC time="2925.60" position="498.98,497.06" type="11" value="0.77"/>
        <maxDRAC time="2925.10" position="498.98,497.06" type="11" value="0.06"/>
        <PET time="NA" position="NA" type="NA" value="NA"/>
    </conflict>
    <conflict begin="2916.20" end="2966.60" ego="L0-HDV-262" foe="L0-HDV-260">
        <minTTC time="2918.90" position="501.60,483.60" type="2" value="1.37"/>
        <maxDRAC time="2916.40" position="501.60,483.60" type="2" value="2.77"/>
        <PET time="NA" position="NA" type="NA" value="NA"/>
    </conflict>
    <conflict begin="2996.80" end="3049.20" ego="L0-HDV-268" foe="L4-CV-424">
        <minTTC time="2997.40" position="543.24,501.60" type="3" value="1.46"/>
        <maxDRAC time="2996.80" position="543.34,501.60" type="3" value="6.03"/>
        <PET time="NA" position="NA" type="NA" value="NA"/>
    </conflict>
    <conflict begin="3009.10" end="3053.30" ego="L0-HDV-271" foe="L2-CV-827">
        <minTTC time="3039.60" position="501.61,503.18" type="11" value="0.79"/>
        <maxDRAC time="3039.50" position="501.61,503.18" type="11" value="0.09"/>
        <PET time="NA" position="NA" type="NA" value="NA"/>
    </conflict>
    <conflict begin="3009.10" end="3072.50" ego="L0-HDV-271" foe="L2-CV-831">
        <minTTC time="3039.80" position="501.61,503.18" type="11" value="0.79"/>
        <maxDRAC time="3009.50" position="501.61,503.18" type="11" value="0.32"/>
        <PET time="NA" position="NA" type="NA" value="NA"/>
    </conflict>
    <conflict begin="3009.10" end="3073.30" ego="L0-HDV-271" foe="L2-CV-826">
        <minTTC time="3039.70" position="501.61,503.18" type="11" value="0.78"/>
        <maxDRAC time="3009.20" position="501.61,503.18" type="11" value="0.23"/>
        <PET time="NA" position="NA" type="NA" value="NA"/>
    </conflict>
    <conflict begin="2972.60" end="3073.40" ego="L0-HDV-267" foe="L2-CV-296">
        <minTTC time="3038.90" position="498.98,497.06" type="11" value="0.63"/>
        <maxDRAC time="2976.10" position="498.98,497.06" type="11" value="0.00"/>
        <PET time="NA" position="NA" type="NA" value="NA"/>
    </conflict>
    <conflict begin="3009.10" end="3073.90" ego="L0-HDV-271" foe="L2-CV-823">
        <minTTC time="3039.70" position="501.61,503.18" type="11" value="0.78"/>
        <maxDRAC time="NA" position="NA" type="NA" value="NA"/>
        <PET time="NA" position="NA" type="NA" value="NA"/>
    </conflict>
    <conflict begin="2972.60" end="3074.10" ego="L0-HDV-267" foe="L4-CV-148">
        <minTTC time="3038.90" position="498.98,497.06" type="11" value="0.63"/>
        <maxDRAC time="2976.00" position="498.98,497.06" type="11" value="0.01"/>
        <PET time="NA" position="NA" type="NA" value="NA"/>
    </conflict>
    <conflict begin="2980.50" end="3072.70" ego="L0-HDV-267" foe="L4-CV-155">
        <minTTC time="3038.80" position="498.98,497.06" type="11" value="0.64"/>
        <maxDRAC time="3038.50" position="498.98,497.06" type="11" value="0.00"/>
        <PET time="NA" position="NA" type="NA" value="NA"/>
    </conflict>
    <conflict begin="2990.40" end="3072.00" ego="L0-HDV-267" foe="L2-CV-314">
        <minTTC time="3038.80" position="498.98,497.06" type="11" value="0.64"/>
        <maxDRAC time="3038.50" position="498.98,497.06" type="11" value="0.00"/>
        <PET time="NA" position="NA" type="NA" value="NA"/>
    </conflict>
    <conflict begin="3009.10" end="3074.60" ego="L0-HDV-271" foe="L2-AV-800">
        <minTTC time="3039.70" position="501.61,503.18" type="11" value="0.78"/>
        <maxDRAC time="NA" position="NA" type="NA" value="NA"/>
        <PET time="NA" position="NA" type="NA" value="NA"/>
    </conflict>
    <conflict begin="3022.50" end="3074.50" ego="L0-HDV-271" foe="L2-AV-853">
        <minTTC time="3039.70" position="501.61,503.18" type="11" value="0.78"/>
        <maxDRAC time="NA" position="NA" type="NA" value="NA"/>
        <PET time="NA" position="NA" type="NA" value="NA"/>
    </conflict>
    <conflict begin="3035.10" end="3073.90" ego="L0-HDV-271" foe="L4-CV-429">
        <minTTC time="3039.70" position="501.61,503.18" type="11" value="0.78"/>
        <maxDRAC time="3036.40" position="506.37,500.57" type="10" value="0.42"/>
        <PET time="NA" position="NA" type="NA" value="NA"/>
    </conflict>
    <conflict begin="3037.00" end="3055.10" ego="L0-HDV-271" foe="L2-AV-833">
        <minTTC time="3039.70" position="501.61,503.18" type="11" value="0.78"/>
        <maxDRAC time="3039.60" position="501.61,503.18" type="11" value="0.02"/>
        <PET time="NA" position="NA" type="NA" value="NA"/>
    </conflict>
    <conflict begin="3037.00" end="3071.60" ego="L0-HDV-271" foe="L2-AV-840">
        <minTTC time="3039.70" position="501.61,503.18" type="11" value="0.78"/>
        <maxDRAC time="NA" position="NA" type="NA" value="NA"/>
        <PET time="NA" position="NA" type="NA" value="NA"/>
    </conflict>
    <conflict begin="3055.40" end="3066.80" ego="L0-HDV-271" foe="L4-CV-425">
        <minTTC time="NA" position="NA" type="NA" value="NA"/>
        <maxDRAC time="NA" position="NA" type="NA" value="NA"/>
        <PET time="3062.85" position="501.61,503.18" type="17" value="1.71"/>
    </conflict>
    <conflict begin="3057.70" end="3068.50" ego="L0-HDV-271" foe="L2-CV-852">
        <minTTC time="3063.00" position="501.74,502.96" type="111" value="0.00"/>
        <maxDRAC time="3062.80" position="501.61,503.18" type="13" value="13.02"/>
        <PET time="3062.85" position="502.20,502.20" type="111" value="0.00"/>
    </conflict>
    <conflict begin="3000.40" end="3052.10" ego="L0-HDV-267" foe="L2-CV-847">
        <minTTC time="3038.70" position="498.98,497.06" type="11" value="0.66"/>
        <maxDRAC time="3038.60" position="498.98,497.06" type="11" value="0.18"/>
        <PET time="NA" position="NA" type="NA" value="NA"/>
    </conflict>
    <conflict begin="3037.00" end="3071.20" ego="L0-HDV-267" foe="L2-AV-327">
        <minTTC time="3038.90" position="498.98,497.06" type="11" value="0.63"/>
        <maxDRAC time="3038.60" position="498.98,497.06" type="11" value="0.00"/>
        <PET time="NA" position="NA" type="NA" value="NA"/>
    </conflict>
    <conflict begin="3037.60" end="3054.60" ego="L0-HDV-267" foe="L2-AV-849">
        <minTTC time="3038.80" position="498.98,497.06" type="11" value="0.64"/>
        <maxDRAC time="3038.50" position="498.98,497.06" type="11" value="0.11"/>
        <PET time="NA" position="NA" type="NA" value="NA"/>
    </conflict>
    <conflict begin="3022.80" end="3114.70" ego="L0-HDV-272" foe="L2-CV-854">
        <minTTC time="3025.70" position="519.60,508.00" type="2" value="1.30"/>
        <maxDRAC time="3023.20" position="519.60,508.00" type="2" value="2.82"/>
        <PET time="NA" position="NA" type="NA" value="NA"/>
    </conflict>
    <conflict begin="2528.80" end="3130.10" ego="L0-HDV-177" foe="L2-AV-554">
        <minTTC time="3004.00" position="473.51,495.20" type="2" value="1.36"/>
        <maxDRAC time="3003.80" position="473.51,495.20" type="2" value="1.60"/>
        <PET time="NA" position="NA" type="NA" value="NA"/>
    </conflict>
    <conflict begin="2534.50" end="3132.40" ego="L0-HDV-177" foe="L4-CV-281">
        <minTTC time="3005.70" position="466.01,495.20" type="3" value="0.99"/>
        <maxDRAC time="3005.60" position="466.01,495.20" type="3" value="1.61"/>
        <PET time="NA" position="NA" type="NA" value="NA"/>
    </conflict>
    <conflict begin="3122.10" end="3197.00" ego="L0-HDV-281" foe="L2-AV-881">
        <minTTC time="3124.70" position="504.80,440.95" type="2" value="1.38"/>
        <maxDRAC time="3122.30" position="504.80,440.05" type="2" value="2.83"/>
        <PET time="NA" position="NA" type="NA" value="NA"/>
    </conflict>
    <conflict begin="3206.90" end="3241.00" ego="L0-HDV-188" foe="L2-AV-899">
        <minTTC time="3224.90" position="495.72,500.95" type="11" value="0.89"/>
        <maxDRAC time="NA" position="NA" type="NA" value="NA"/>
        <PET time="NA" position="NA" type="NA" value="NA"/>
    </conflict>
    <conflict begin="3206.90" end="3241.00" ego="L0-HDV-188" foe="L2-CV-907">
        <minTTC time="3224.90" position="495.72,500.95" type="11" value="0.89"/>
        <maxDRAC time="3207.70" position="499.54,506.64" type="10" value="0.34"/>
        <PET time="NA" position="NA" type="NA" value="NA"/>
    </conflict>
    <conflict begin="3206.90" end="3240.40" ego="L0-HDV-188" foe="L4-CV-452">
        <minTTC time="3224.90" position="495.72,500.95" type="11" value="0.89"/>
        <maxDRAC time="3211.80" position="495.72,500.95" type="11" value="0.00"/>
        <PET time="NA" position="NA" type="NA" value="NA"/>
    </conflict>
    <conflict begin="3211.50" end="3233.60" ego="L0-HDV-188" foe="L2-AV-865">
        <minTTC time="3212.40" position="495.72,500.95" type="11" value="5.63"/>
        <maxDRAC time="3224.10" position="495.72,500.95" type="11" value="0.79"/>
        <PET time="3228.82" position="495.72,500.95" type="17" value="0.90"/>
    </conflict>
    <conflict begin="3219.10" end="3239.30" ego="L0-HDV-188" foe="L2-CV-869">
        <minTTC time="3223.50" position="495.72,500.95" type="11" value="1.35"/>
        <maxDRAC time="3223.70" position="495.72,500.95" type="11" value="0.33"/>
        <PET time="NA" position="NA" type="NA" value="NA"/>
    </conflict>
    <conflict begin="3222.70" end="3238.50" ego="L0-HDV-188" foe="L2-AV-869">
        <minTTC time="3224.40" position="495.72,500.95" type="11" value="1.00"/>
        <maxDRAC time="3224.60" position="495.72,500.95" type="11" value="0.18"/>
        <PET time="NA" position="NA" type="NA" value="NA"/>
    </conflict>
    <conflict begin="3080.60" end="3348.10" ego="L0-HDV-204" foe="L2-AV-634">
        <minTTC time="3229.60" position="480.40,495.20" type="2" value="1.40"/>
        <maxDRAC time="3081.10" position="249.33,492.00" type="2" value="1.49"/>
        <PET time="NA" position="NA" type="NA" value="NA"/>
    </conflict>
    <conflict begin="3068.00" end="3360.20" ego="L0-HDV-201" foe="L4-CV-315">
        <minTTC time="3071.30" position="292.45,498.40" type="2" value="1.49"/>
        <maxDRAC time="3069.80" position="291.04,498.40" type="2" value="2.11"/>
        <PET time="NA" position="NA" type="NA" value="NA"/>
    </conflict>
    <conflict begin="3443.70" end="3461.70" ego="L0-HDV-309" foe="L0-HDV-304">
        <minTTC time="3452.30" position="504.53,499.70" type="11" value="0.85"/>
        <maxDRAC time="NA" position="NA" type="NA" value="NA"/>
        <PET time="NA" position="NA" type="NA" value="NA"/>
    </conflict>
    <conflict begin="3443.70" end="3462.30" ego="L0-HDV-309" foe="L2-AV-954">
        <minTTC time="3452.30" position="504.53,499.70" type="11" value="0.85"/>
        <maxDRAC time="NA" position="NA" type="NA" value="NA"/>
        <PET time="NA" position="NA" type="NA" value="NA"/>
    </conflict>
    <conflict begin="3443.70" end="3461.10" ego="L0-HDV-309" foe="L2-AV-959">
        <minTTC time="3452.30" position="504.53,499.70" type="11" value="0.85"/>
        <maxDRAC time="3450.40" position="504.00,498.49" type="10" value="0.00"/>
        <PET time="NA" position="NA" type="NA" value="NA"/>
    </conflict>
    <conflict begin="3443.70" end="3460.50" ego="L0-HDV-309" foe="L2-CV-960">
        <minTTC time="3452.30" position="504.53,499.70" type="11" value="0.85"/>
        <maxDRAC time="3450.40" position="504.00,498.49" type="10" value="0.00"/>
        <PET time="NA" position="NA" type="NA" value="NA"/>
    </conflict>
    <conflict begin="3443.70" end="3462.40" ego="L0-HDV-309" foe="L4-CV-485">
        <minTTC time="3452.30" position="504.53,499.70" type="11" value="0.85"/>
        <maxDRAC time="NA" position="NA" type="NA" value="NA"/>
        <PET time="NA" position="NA" type="NA" value="NA"/>
    </conflict>
    <conflict begin="3441.60" end="3465.00" ego="L0-HDV-295" foe="L2-CV-625">
        <minTTC time="3451.00" position="499.06,503.01" type="11" value="8.50"/>
        <maxDRAC time="NA" position="NA" type="NA" value="NA"/>
        <PET time="3457.19" position="495.72,500.95" type="17" value="1.03"/>
    </conflict>
    <conflict begin="3487.00" end="3507.80" ego="L0-HDV-314" foe="L0-HDV-311">
        <minTTC time="3489.80" position="495.20,547.95" type="2" value="1.35"/>
        <maxDRAC time="3487.00" position="495.20,548.87" type="2" value="2.94"/>
        <PET time="NA" position="NA" type="NA" value="NA"/>
    </conflict>
    <conflict begin="3487.00" end="3507.80" ego="L0-HDV-311" foe="L0-HDV-314">
        <minTTC time="3489.80" position="495.20,547.95" type="3" value="1.35"/>
        <maxDRAC time="3487.00" position="495.20,548.87" type="3" value="2.94"/>
        <PET time="NA" position="NA" type="NA" value="NA"/>
    </conflict>
    <conflict begin="3533.20" end="3616.60" ego="L0-HDV-319" foe="L2-AV-1000">
        <minTTC time="3537.00" position="501.60,436.57" type="2" value="1.43"/>
        <maxDRAC time="3537.00" position="501.60,436.57" type="2" value="3.01"/>
        <PET time="NA" position="NA" type="NA" value="NA"/>
    </conflict>
    <conflict begin="3667.10" end="3684.40" ego="L0-HDV-201" foe="L2-CV-992">
        <minTTC time="3674.30" position="499.06,503.01" type="10" value="7.69"/>
        <maxDRAC time="3674.40" position="495.72,500.95" type="11" value="0.65"/>
        <PET time="3679.91" position="495.72,500.95" type="17" value="1.11"/>
    </conflict>
    <conflict begin="3673.30" end="3691.60" ego="L0-HDV-201" foe="L2-CV-1001">
        <minTTC time="3674.60" position="495.72,500.95" type="11" value="0.65"/>
        <maxDRAC time="3674.70" position="495.72,500.95" type="11" value="0.27"/>
        <PET time="NA" position="NA" type="NA" value="NA"/>
    </conflict>
    <conflict begin="3360.00" end="3697.50" ego="L0-HDV-305" foe="L4-CV-480">
        <minTTC time="3391.20" position="629.00,504.80" type="3" value="1.06"/>
        <maxDRAC time="3390.70" position="629.35,504.80" type="3" value="1.60"/>
        <PET time="NA" position="NA" type="NA" value="NA"/>
    </conflict>
    <conflict begin="3559.30" end="3672.50" ego="L0-HDV-305" foe="L2-AV-647">
        <minTTC time="3659.80" position="499.06,503.01" type="11" value="1.20"/>
        <maxDRAC time="3659.90" position="495.72,500.95" type="10" value="3.00"/>
        <PET time="NA" position="NA" type="NA" value="NA"/>
    </conflict>
    <conflict begin="3659.50" end="3679.30" ego="L0-HDV-310" foe="L2-AV-647">
        <minTTC time="3669.80" position="495.72,500.95" type="10" value="0.72"/>
        <maxDRAC time="3669.80" position="495.72,500.95" type="10" value="0.60"/>
        <PET time="3671.64" position="495.72,500.95" type="17" value="0.73"/>
    </conflict>
    <conflict begin="3556.50" end="3778.60" ego="L0-HDV-321" foe="L2-CV-1004">
        <minTTC time="3559.50" position="645.39,504.80" type="2" value="1.45"/>
        <maxDRAC time="3556.60" position="645.93,504.80" type="2" value="2.52"/>
        <PET time="NA" position="NA" type="NA" value="NA"/>
    </conflict>
    <conflict begin="3501.10" end="3785.00" ego="L0-HDV-215" foe="L2-CV-692">
        <minTTC time="3503.80" position="382.16,498.40" type="2" value="1.23"/>
        <maxDRAC time="3501.10" position="382.16,498.40" type="2" value="3.08"/>
        <PET time="NA" position="NA" type="NA" value="NA"/>
    </conflict>
    <conflict begin="3509.90" end="3795.50" ego="L0-HDV-215" foe="L2-CV-694">
        <minTTC time="3512.80" position="375.06,498.40" type="3" value="1.40"/>
        <maxDRAC time="3510.00" position="374.86,498.40" type="3" value="2.65"/>
        <PET time="NA" position="NA" type="NA" value="NA"/>
    </conflict>
    <conflict begin="3341.90" end="3448.60" ego="L0-HDV-216" foe="L4-CV-337">
        <minTTC time="3344.60" position="343.15,498.40" type="2" value="1.26"/>
        <maxDRAC time="3342.60" position="343.14,498.40" type="2" value="2.76"/>
        <PET time="NA" position="NA" type="NA" value="NA"/>
    </conflict>
    <conflict begin="3353.20" end="3481.30" ego="L0-HDV-216" foe="L2-CV-684">
        <minTTC time="3355.90" position="335.65,498.40" type="3" value="1.29"/>
        <maxDRAC time="3354.10" position="335.65,498.40" type="3" value="2.94"/>
        <PET time="NA" position="NA" type="NA" value="NA"/>
    </conflict>
    <conflict begin="3814.00" end="3853.40" ego="L0-HDV-247" foe="L2-AV-767">
        <minTTC time="3840.40" position="62.48,492.00" type="2" value="1.32"/>
        <maxDRAC time="3839.90" position="62.36,492.00" type="2" value="2.09"/>
        <PET time="NA" position="NA" type="NA" value="NA"/>
    </conflict>
    <conflict begin="3857.10" end="3926.20" ego="L0-HDV-247" foe="L2-AV-767">
        <minTTC time="3859.70" position="115.67,492.00" type="2" value="1.09"/>
        <maxDRAC time="3858.30" position="115.67,492.00" type="2" value="3.36"/>
        <PET time="NA" position="NA" type="NA" value="NA"/>
    </conflict>
    <conflict begin="4206.80" end="4274.00" ego="L0-HDV-285" foe="L2-AV-888">
        <minTTC time="4248.90" position="355.00,498.40" type="2" value="1.28"/>
        <maxDRAC time="4248.90" position="355.00,498.40" type="2" value="1.32"/>
        <PET time="NA" position="NA" type="NA" value="NA"/>
    </conflict>
    <conflict begin="4207.20" end="4227.80" ego="L0-HDV-285" foe="L4-AV-444">
        <minTTC time="4210.30" position="78.73,492.00" type="2" value="1.18"/>
        <maxDRAC time="4208.90" position="78.68,492.00" type="2" value="2.69"/>
        <PET time="NA" position="NA" type="NA" value="NA"/>
    </conflict>
    <conflict begin="3540.90" end="4541.70" ego="L0-HDV-234" foe="L4-AV-370">
        <minTTC time="4459.60" position="472.81,498.40" type="3" value="1.47"/>
        <maxDRAC time="4459.40" position="472.76,498.40" type="3" value="0.60"/>
        <PET time="NA" position="NA" type="NA" value="NA"/>
    </conflict>
    <conflict begin="4392.40" end="4639.70" ego="L0-HDV-250" foe="L2-CV-966">
        <minTTC time="4563.70" position="465.40,498.40" type="3" value="1.37"/>
        <maxDRAC time="4563.50" position="465.40,498.40" type="3" value="1.59"/>
        <PET time="NA" position="NA" type="NA" value="NA"/>
    </conflict>
</SSMLog>
